Metadata-Version: 2.1
Name: hpglobal
Version: 1.20181217
Summary: hpformula for lyy
Author: lyy
Author-email: 
License: MIT
License-File: LICENSE
